yfm/__init__.py
yfm/yfMongo.py
yfm/yfmTest.py
yfm/yfmcli.py
yfm/YahooFetcher/ComponentsExtractor.py
yfm/YahooFetcher/QueryBuilder.py
yfm/YahooFetcher/YahooFetcher.py
yfm/YahooFetcher/__init__.py
yfm/YahooFetcher/sampleMSFT.py
yfm/YahooFetcher/test.py
yfm-1.3.8.dist-info/DESCRIPTION.rst
yfm-1.3.8.dist-info/METADATA
yfm-1.3.8.dist-info/RECORD
yfm-1.3.8.dist-info/WHEEL
yfm-1.3.8.dist-info/entry_points.txt
yfm-1.3.8.dist-info/metadata.json
yfm-1.3.8.dist-info/top_level.txt
